{
  "entities": [
    {
      "start": 25,
      "end": 42,
      "label": "COMPANY"
    },
    {
      "start": 43,
      "end": 81,
      "label": "FIO_D_2"
    },
    {
      "start": 88,
      "end": 132,
      "label": "FIO_R_1"
    },
    {
      "start": 243,
      "end": 285,
      "label": "FIO_I_1"
    },
    {
      "start": 517,
      "end": 567,
      "label": "FIO_I_3"
    },
    {
      "start": 569,
      "end": 574,
      "label": "DATE_2"
    },
    {
      "start": 669,
      "end": 688,
      "label": "DATE_3"
    },
    {
      "start": 828,
      "end": 846,
      "label": "PHONE_1"
    },
    {
      "start": 847,
      "end": 865,
      "label": "PHONE_2"
    },
    {
      "start": 1003,
      "end": 1010,
      "label": "DATE_1"
    },
    {
      "start": 1047,
      "end": 1089,
      "label": "FIO_I_1"
    },
    {
      "start": 1127,
      "end": 1161,
      "label": "FIO_I_2"
    }
  ]
}